[
  {
    "id": "tile_001",
    "title": "Ceramic Blue Tile",
    "description": "Premium ceramic tile with blue glaze finish",
    "image": "https://www.kajariaceramics.com/storage/product_attributes/blend.webp",
    "category": "ceramic",
    "price": 45.99,
    "currency": "USD",
    "dimensions": "60x60 cm",
    "material": "Ceramic",
    "inStock": true
  },
  {
    "id": "tile_002",
    "title": "Marble White Tile",
    "description": "Elegant white marble tile with natural veins",
    "image": "https://www.kajariaceramics.com/storage/product_attributes/bold.webp",
    "category": "marble",
    "price": 75.5,
    "currency": "USD",
    "dimensions": "80x80 cm",
    "material": "Marble",
    "inStock": true
  },
  {
    "id": "tile_003",
    "title": "Granite Black Tile",
    "description": "Durable granite tile with black polished finish",
    "image": "https://www.kajariaceramics.com/storage/product_attributes/bliss.webp",
    "category": "granite",
    "price": 65.0,
    "currency": "USD",
    "dimensions": "60x60 cm",
    "material": "Granite",
    "inStock": false
  },
  {
    "id": "tile_004",
    "title": "Porcelain Grey Tile",
    "description": "Modern grey porcelain tile for interiors",
    "image": "https://www.kajariaceramics.com/storage/product_attributes/carving.webp",
    "category": "porcelain",
    "price": 50.25,
    "currency": "USD",
    "dimensions": "60x120 cm",
    "material": "Porcelain",
    "inStock": true
  },
  {
    "id": "tile_005",
    "title": "Wood Finish Tile",
    "description": "Wood-style tile with natural texture",
    "image": "https://www.kajariaceramics.com/storage/product_attributes/hd-polished.webp",
    "category": "wood",
    "price": 55.75,
    "currency": "USD",
    "dimensions": "20x120 cm",
    "material": "Porcelain",
    "inStock": true
  },
  {
    "id": "tile_006",
    "title": "Glossy Beige Tile",
    "description": "Smooth glossy tile with beige tone",
    "image": "https://www.kajariaceramics.com/storage/product_attributes/high-gloss.webp",
    "category": "ceramic",
    "price": 42.0,
    "currency": "USD",
    "dimensions": "60x60 cm",
    "material": "Ceramic",
    "inStock": true
  },
  {
    "id": "tile_007",
    "title": "Rustic Brown Tile",
    "description": "Rustic style tile with earthy brown color",
    "image": "https://www.kajariaceramics.com/storage/product_attributes/polish.webp",
    "category": "ceramic",
    "price": 38.9,
    "currency": "USD",
    "dimensions": "45x45 cm",
    "material": "Ceramic",
    "inStock": false
  },
  {
    "id": "tile_008",
    "title": "Polished Marble Tile",
    "description": "High-gloss polished marble tile",
    "image": "https://www.kajariaceramics.com/storage/product_attributes/super-glossy.webp",
    "category": "marble",
    "price": 85.0,
    "currency": "USD",
    "dimensions": "100x100 cm",
    "material": "Marble",
    "inStock": true
  },
  {
    "id": "tile_009",
    "title": "Textured Stone Tile",
    "description": "Stone tile with textured surface",
    "image": "https://www.kajariaceramics.com/storage/product_attributes/ultra-matt.webp",
    "category": "stone",
    "price": 60.0,
    "currency": "USD",
    "dimensions": "60x60 cm",
    "material": "Stone",
    "inStock": true
  },
  {
    "id": "tile_010",
    "title": "Matte Black Tile",
    "description": "Minimal matte black tile for modern design",
    "image": "https://www.kajariaceramics.com/storage/product_attributes/ultra-polish.webp",
    "category": "porcelain",
    "price": 58.5,
    "currency": "USD",
    "dimensions": "60x60 cm",
    "material": "Porcelain",
    "inStock": true
  },
  {
    "id": "tile_011",
    "title": "Patterned Mosaic Tile",
    "description": "Decorative mosaic tile with patterns",
    "image": "https://www.kajariaceramics.com/storage/concept-picture/E00000001057.jpg",
    "category": "mosaic",
    "price": 70.0,
    "currency": "USD",
    "dimensions": "30x30 cm",
    "material": "Glass",
    "inStock": true
  },
  {
    "id": "tile_012",
    "title": "Outdoor Rough Tile",
    "description": "Slip-resistant tile for outdoor use",
    "image": "https://www.kajariaceramics.com/storage/concept-picture/E00000001058.jpg",
    "category": "outdoor",
    "price": 52.3,
    "currency": "USD",
    "dimensions": "60x60 cm",
    "material": "Concrete",
    "inStock": true
  },
  {
    "id": "tile_013",
    "title": "Luxury Gold Tile",
    "description": "Premium tile with golden finish",
    "image": "https://www.kajariaceramics.com/storage/concept-picture/E00000000859.jpg",
    "category": "luxury",
    "price": 120.0,
    "currency": "USD",
    "dimensions": "80x80 cm",
    "material": "Porcelain",
    "inStock": false
  },
  {
    "id": "tile_014",
    "title": "Classic White Tile",
    "description": "Simple and classic white tile",
    "image": "https://www.kajariaceramics.com/storage/concept-picture/E00000000864.jpg",
    "category": "ceramic",
    "price": 30.0,
    "currency": "USD",
    "dimensions": "50x50 cm",
    "material": "Ceramic",
    "inStock": true
  },
  {
    "id": "tile_015",
    "title": "Dark Grey Tile",
    "description": "Dark grey tile with smooth finish",
    "image": "https://www.kajariaceramics.com/storage/concept-picture/E00000000711.jpg",
    "category": "porcelain",
    "price": 48.0,
    "currency": "USD",
    "dimensions": "60x60 cm",
    "material": "Porcelain",
    "inStock": true
  },
  {
    "id": "tile_016",
    "title": "Natural Stone Tile",
    "description": "Natural stone tile for elegant look",
    "image": "https://www.kajariaceramics.com/storage/concept-picture/E00000000704.jpg",
    "category": "stone",
    "price": 68.0,
    "currency": "USD",
    "dimensions": "70x70 cm",
    "material": "Stone",
    "inStock": true
  },
  {
    "id": "tile_017",
    "title": "Glossy Red Tile",
    "description": "Bright red glossy ceramic tile",
    "image": "https://www.kajariaceramics.com/storage/concept-picture/E00000000720.jpg",
    "category": "ceramic",
    "price": 44.0,
    "currency": "USD",
    "dimensions": "60x60 cm",
    "material": "Ceramic",
    "inStock": false
  },
  {
    "id": "tile_018",
    "title": "Minimal Cream Tile",
    "description": "Soft cream tile for minimal interiors",
    "image": "https://www.kajariaceramics.com/storage/concept-picture/arizona-marfil-1.jpg",
    "category": "ceramic",
    "price": 36.5,
    "currency": "USD",
    "dimensions": "60x60 cm",
    "material": "Ceramic",
    "inStock": true
  },
  {
    "id": "tile_019",
    "title": "Industrial Concrete Tile",
    "description": "Industrial style concrete look tile",
    "image": "https://www.kajariaceramics.com/storage/concept-picture/artek-nero-1.jpg",
    "category": "industrial",
    "price": 62.0,
    "currency": "USD",
    "dimensions": "60x120 cm",
    "material": "Concrete",
    "inStock": true
  },
  {
    "id": "tile_020",
    "title": "Luxury Marble Black Tile",
    "description": "Black marble tile with luxury finish",
    "image": "https://www.kajariaceramics.com/storage/concept-picture/pezatto-rozo-1.jpg",
    "category": "marble",
    "price": 95.0,
    "currency": "USD",
    "dimensions": "100x100 cm",
    "material": "Marble",
    "inStock": true
  }
]
